{
  "publications": [
    {
      "id": "wilddet3d",
      "title": "WildDet3D: Scaling Promptable 3D Detection in the Wild",
      "authors": [
        "Weikai Huang\u2665",
        "Jieyu Zhang\u2665",
        "Sijun Li",
        "Taoyang Jia",
        "Jiafei Duan",
        "Yunqian Cheng",
        "Jaemin Cho",
        "Matthew Wallingford",
        "Rustin Soraki",
        "Chris Dongjoo Kim",
        "Shuo Liu",
        "Donovan Clay",
        "Taira Anderson",
        "Winson Han",
        "Ali Farhadi",
        "Bharath Hariharan",
        "Zhongzheng Ren\u2665",
        "Ranjay Krishna\u2665"
      ],
      "venue": "Arxiv",
      "year": "2026",
      "video": "https://www.youtube.com/watch?v=RgHKmOqb7I4",
      "github_repo": "allenai/WildDet3D",
      "links": {
        "website": "https://allenai.github.io/WildDet3D/",
        "code": "https://github.com/allenai/WildDet3D",
        "huggingface": "https://huggingface.co/collections/allenai/wilddet3d-69d42220ec4f942f1951263e",
        "demo": "https://huggingface.co/spaces/allenai/WildDet3D",
        "data": "https://huggingface.co/datasets/allenai/WildDet3D-Data",
        "blog": "https://allenai.org/blog/wilddet3d",
        "app": "https://apps.apple.com/us/app/wilddet3d/id6760861157"
      },
      "selected": true,
      "tldr": "Unified promptable 3D detection model supporting text, box, and point prompts with optional depth input. Trained on 1M+ in-the-wild images with 13.5K categories. Deployed on iPhone, Meta Quest, and robotics platforms.",
      "github_stars": 0,
      "citations": 0
    },
    {
      "id": "sos",
      "title": "Synthetic Object Compositions for Scalable and Accurate Learning in Detection, Segmentation, and Grounding",
      "authors": [
        "Weikai Huang",
        "Jieyu Zhang",
        "Taoyang Jia",
        "Chenhao Zheng",
        "Ziqi Gao",
        "Jae Sung Park",
        "Winson Han",
        "Ranjay Krishna"
      ],
      "venue": "CVPR",
      "year": "2026",
      "image": "img/papers/sos.png",
      "arxiv_id": "2510.09110",
      "github_repo": "weikaih04/Synthetic-Detection-Segmentation-Grounding-Data",
      "links": {
        "arxiv": "https://arxiv.org/abs/2510.09110",
        "website": "https://github.com/weikaih04/Synthetic-Detection-Segmentation-Grounding-Data",
        "code": "https://github.com/weikaih04/Synthetic-Detection-Segmentation-Grounding-Data",
        "huggingface": "https://huggingface.co/collections/weikaih/sos-synthetic-object-segments-improves-detection-segmentat-682679751d20faa20800033c"
      },
      "selected": true,
      "tldr": "1M diverse and dense-annotated synthetic images composed by 20M synthetic object—boost GroundingDINO, Mask2Former on LVIS, gRefCOCO. First synthetic dataset surpassing real datasets in different models / benchmarks.",
      "github_stars": 80,
      "citations": 0
    }
  ]
}
